pyscx/__init__.py
pyscx/api.py
pyscx/exceptions.py
pyscx/github/__init__.py
pyscx/http.py
pyscx/methods.py
pyscx/objects.py
pyscx/token.py
pyscx-1.1.3.dist-info/LICENSE
pyscx-1.1.3.dist-info/METADATA
pyscx-1.1.3.dist-info/WHEEL
pyscx-1.1.3.dist-info/RECORD
