Metadata-Version: 2.3
Name: pyscx
Version: 1.1.3
Summary: A library for interacting with the STALCRAFT: X API
License: LICENSE
Keywords: api,library,eapi,stalcraft,package
Author: Oidaho
Author-email: oidaho.main@yandex.ru
Requires-Python: >=3.13
Classifier: Development Status :: 5 - Production/Stable
Classifier: Intended Audience :: Developers
Classifier: License :: OSI Approved :: GNU General Public License v3 (GPLv3)
Classifier: License :: Other/Proprietary License
Classifier: Natural Language :: English
Classifier: Natural Language :: Russian
Classifier: Programming Language :: Python
Classifier: Programming Language :: Python :: 3
Classifier: Programming Language :: Python :: 3.13
Classifier: Topic :: Games/Entertainment
Classifier: Topic :: Software Development :: Libraries :: Python Modules
Requires-Dist: cachetools (>=5.5.1,<6.0.0)
Requires-Dist: pydantic (>=2.10.6,<3.0.0)
Requires-Dist: requests (>=2.32.3,<3.0.0)
Project-URL: Bug Tracker, https://github.com/Oidaho/pyscx/issues
Project-URL: Documentation, https://Oidaho.github.io/pyscx/
Project-URL: Repository, https://github.com/Oidaho/pyscx
